{
  "version": 1,
  "clusterName": "192.168.64.74:8443",
  "namespace": "myproject",
  "clientId": "example_client_id",
  "services": [
    {
      "id": "keycloak",
      "name": "keycloak",
      "type": "keycloak",
      "url": "https://keycloak.security.feedhenry.org/auth/",
      "config": {
        "realm": "secure-app",
        "url": "https://keycloak.security.feedhenry.org/auth/",
        "ssl-required": "external",
        "clientId": "client-app",
        "public-client": true,
        "use-resource-role-mappings": true,
        "pinningFingerprint": "44 C8 9A 60 4E 29 82 85 8E 4F 75 1F 78 46 CD B3 0A 08 66 3F",
        "apiServerUrl": "https://api.security.feedhenry.org",
        "apiEndpoint": "/"
      }
    },
    {
      "id": "metrics",
      "name": "metrics",
      "type": "metrics",
      "url": "https://www.mocky.io/v2/5aa696133100001335e716e0",
      "config": {}
    },
    {
      "id": "push",
      "name": "push",
      "type": "push",
      "url": "https://ups-dm-myproject-1.193b.starter-ca-central-1.openshiftapps.com/",
      "config": {
        "ios": {
          "variantId": "f85015b4-a762-49a7-a36f-34a451f819a4",
          "variantSecret": "978b35d6-7058-43b4-8c37-4dc30022ebda"
        },
        "android": {
          "variantId": "795d5953-558c-4026-9407-194169fbf7fa",
          "variantSecret": "92fd41dd-505b-4513-aaea-d02e27251695",
          "senderId": "754329551899"
        }
      }
    }
  ]
}



